MANIFEST.in
README.rst
setup.py
docs/HISTORY.txt
docs/LICENSE.GPL
docs/LICENSE.txt
ftw/__init__.py
ftw.topics.egg-info/PKG-INFO
ftw.topics.egg-info/SOURCES.txt
ftw.topics.egg-info/dependency_links.txt
ftw.topics.egg-info/entry_points.txt
ftw.topics.egg-info/namespace_packages.txt
ftw.topics.egg-info/not-zip-safe
ftw.topics.egg-info/requires.txt
ftw.topics.egg-info/top_level.txt
ftw/topics/__init__.py
ftw/topics/behavior.py
ftw/topics/collector.py
ftw/topics/configure.zcml
ftw/topics/finder.py
ftw/topics/interfaces.py
ftw/topics/lawgiver.zcml
ftw/topics/permissions.zcml
ftw/topics/restapi.py
ftw/topics/testing.py
ftw/topics/Extensions/install.py
ftw/topics/browser/__init__.py
ftw/topics/browser/configure.zcml
ftw/topics/browser/representation.py
ftw/topics/browser/resources.zcml
ftw/topics/browser/topic.py
ftw/topics/browser/tree.py
ftw/topics/browser/viewlet.py
ftw/topics/browser/contentpage/__init__.py
ftw/topics/browser/contentpage/contentpage_representation.pt
ftw/topics/browser/contentpage/representation.py
ftw/topics/browser/resources/ftwtheming.scss
ftw/topics/browser/resources/icon.png
ftw/topics/browser/templates/default_representation.pt
ftw/topics/browser/templates/topic.pt
ftw/topics/browser/templates/topic_listing.pt
ftw/topics/browser/templates/tree.pt
ftw/topics/browser/templates/viewlet.pt
ftw/topics/contents/__init__.py
ftw/topics/contents/topic.py
ftw/topics/contents/tree.py
ftw/topics/locales/ftw.topics.pot
ftw/topics/locales/plone.pot
ftw/topics/locales/de/LC_MESSAGES/ftw.topics.po
ftw/topics/locales/de/LC_MESSAGES/plone.po
ftw/topics/profiles/default/browserlayer.xml
ftw/topics/profiles/default/metadata.xml
ftw/topics/profiles/default/rolemap.xml
ftw/topics/profiles/default/types.xml
ftw/topics/profiles/default/types/ftw.topics.Topic.xml
ftw/topics/profiles/default/types/ftw.topics.TopicTree.xml
ftw/topics/profiles/uninstall/browserlayer.xml
ftw/topics/profiles/uninstall/rolemap.xml
ftw/topics/profiles/uninstall/types.xml
ftw/topics/tests/__init__.py
ftw/topics/tests/builders.py
ftw/topics/tests/functional_tests.zcml
ftw/topics/tests/test_behavior.py
ftw/topics/tests/test_browserlayer.py
ftw/topics/tests/test_collector.py
ftw/topics/tests/test_content_types.py
ftw/topics/tests/test_finder.py
