Metadata-Version: 2.1
Name: ftw.topics
Version: 2.2.2
Summary: Create subject trees in Plone
Home-page: https://github.com/4teamwork/ftw.topics
Author: 4teamwork AG
Author-email: mailto:info@4teamwork.ch
License: GPL2
Keywords: ftw topics
Platform: UNKNOWN
Classifier: Framework :: Plone
Classifier: Framework :: Plone :: 4.3
Classifier: Framework :: Plone :: 5.1
Classifier: Intended Audience :: Developers
Classifier: Topic :: Software Development :: Libraries :: Python Modules
Provides-Extra: restapi
Provides-Extra: tests
